json_trek/__init__.py
json_trek/main.py
json_trek/test_json_trek.py
json_trek/json/animals.json
json_trek/json/astronomical_objects.json
json_trek/json/klingon_words.json
json_trek/json/names.json
json_trek/json/occupations.json
json_trek/json/species.json
json_trek/json/trek_nouns.json
json_trek-1.0.9.dist-info/METADATA
json_trek-1.0.9.dist-info/WHEEL
json_trek-1.0.9.dist-info/top_level.txt
json_trek-1.0.9.dist-info/RECORD
