Metadata-Version: 2.1
Name: json_trek
Version: 1.0.9
Summary: Generate fake JSON user data and lorem ipsum with a Star Trek theme.
Home-page: UNKNOWN
Author: Keegan Good
Author-email: keegood8@gmail.com
License: MIT
Project-URL: Source, https://github.com/perennialAutodidact/json_trek
Platform: UNKNOWN
Classifier: Development Status :: 5 - Production/Stable
Classifier: Programming Language :: Python :: 3
Classifier: Programming Language :: Python :: 3.6
Classifier: Programming Language :: Python :: 3.7
Classifier: Programming Language :: Python :: 3.8
Classifier: Programming Language :: Python :: 3.9
Classifier: Programming Language :: Python :: 3.10
Classifier: Environment :: Web Environment
Classifier: Intended Audience :: Developers
Classifier: License :: OSI Approved :: MIT License
Classifier: Natural Language :: English
Classifier: Topic :: Utilities
Classifier: Operating System :: OS Independent
Requires-Python: >=3.6
